Metadata-Version: 2.4
Name: jira-ticket-validator
Version: 0.1.0
Summary: Un validador de tickets de Jira que verifica atributos y subtareas.
Home-page: https://github.com/BrigitteMendez1302/jira-ticket-validator
Author: Brigitte Mendez
Author-email: mendezbrigitte13@gmail.com
Classifier: Programming Language :: Python :: 3
Classifier: License :: OSI Approved :: MIT License
Classifier: Operating System :: OS Independent
Requires-Python: >=3.7
Requires-Dist: jira
Dynamic: author
Dynamic: author-email
Dynamic: classifier
Dynamic: description
Dynamic: description-content-type
Dynamic: home-page
Dynamic: requires-dist
Dynamic: requires-python
Dynamic: summary
